setup.py
ncc_paapi.egg-info/PKG-INFO
ncc_paapi.egg-info/SOURCES.txt
ncc_paapi.egg-info/dependency_links.txt
ncc_paapi.egg-info/requires.txt
ncc_paapi.egg-info/top_level.txt
paapi/__init__.py
paapi/paapi.py