Metadata-Version: 1.0
Name: ncc-paapi
Version: 0.0.3
Summary: Abstraction classes to access the PA API
Home-page: https://github.com/ncc-tools/python-pa-api
Author: NCC Group
Author-email: UNKNOWN
License: UNKNOWN
Platform: UNKNOWN
